generate_docstring/__init__.py
generate_docstring/__main__.py
generate_docstring/parser.py
generate_docstring/templates/class_def.py.jinja2
generate_docstring/templates/function_def.py.jinja2
generate_docstring/templates/module.py.jinja2
generate_docstring/transformer.py
generate_docstring/visitor.py
generate_docstring-0.1.1.dist-info/WHEEL
generate_docstring-0.1.1.dist-info/METADATA
generate_docstring-0.1.1.dist-info/RECORD
