Metadata-Version: 2.1
Name: generate-docstring
Version: 0.1.1
Summary: 
Author: manslaughter03
Author-email: manslaughter03@gmail.com
Requires-Python: >=3.7,<4.0
Classifier: Programming Language :: Python :: 3
Classifier: Programming Language :: Python :: 3.10
Classifier: Programming Language :: Python :: 3.7
Classifier: Programming Language :: Python :: 3.8
Classifier: Programming Language :: Python :: 3.9
Requires-Dist: Jinja2 (>=3.1.1,<4.0.0)
Requires-Dist: libcst (>=0.4.1,<0.5.0)
